adhawkapi/__init__.py
adhawkapi/error.py
adhawkapi/publicapi.py
adhawkapi/frontend/__init__.py
adhawkapi/frontend/backendcom.py
adhawkapi/frontend/decoders.py
adhawkapi/frontend/encoders.py
adhawkapi/frontend/frontend_api.py
adhawkapi/frontend/handlers.py
adhawkapi/frontend/video_receiver.py
adhawk-6.5.dist-info/LICENSE.md
adhawk-6.5.dist-info/METADATA
adhawk-6.5.dist-info/WHEEL
adhawk-6.5.dist-info/top_level.txt
adhawk-6.5.dist-info/RECORD
