Metadata-Version: 2.1
Name: adhawk
Version: 6.5
Summary: AdHawk Microsystems SDK
Home-page: http://www.adhawkmicrosystems.com/
Author: AdHawk Microsystems
Author-email: info@adhawkmicrosystems.com
License: Proprietary
Classifier: Programming Language :: Python :: 3
Classifier: License :: Other/Proprietary License
Classifier: Operating System :: OS Independent
Requires-Python: >=3.9
License-File: LICENSE.md
Requires-Dist: numpy
